atlassian_mcp_server/__init__.py
atlassian_mcp_server/__main__.py
atlassian_mcp_server/module_manager.py
atlassian_mcp_server/server.py
atlassian_mcp_server/clients/__init__.py
atlassian_mcp_server/clients/base_client.py
atlassian_mcp_server/clients/confluence_client.py
atlassian_mcp_server/clients/jira_client.py
atlassian_mcp_server/clients/service_desk_client.py
atlassian_mcp_server/modules/__init__.py
atlassian_mcp_server/modules/base.py
atlassian_mcp_server/modules/confluence.py
atlassian_mcp_server/modules/jira.py
atlassian_mcp_server/modules/service_desk.py
atlassian_mcp_server-0.4.3.dist-info/licenses/LICENSE
atlassian_mcp_server-0.4.3.dist-info/METADATA
atlassian_mcp_server-0.4.3.dist-info/WHEEL
atlassian_mcp_server-0.4.3.dist-info/entry_points.txt
atlassian_mcp_server-0.4.3.dist-info/top_level.txt
atlassian_mcp_server-0.4.3.dist-info/RECORD
