Metadata-Version: 2.4
Name: atlassian-mcp-server
Version: 0.4.3
Summary: MCP server for Atlassian Cloud (Confluence & Jira) with seamless OAuth 2.0 authentication
Author-email: Rory McMahon <rory.mcmahon@vocus.com.au>
License: MIT
Project-URL: Homepage, https://github.com/InfraMCP/atlassian-mcp-server
Project-URL: Repository, https://github.com/InfraMCP/atlassian-mcp-server
Project-URL: Issues, https://github.com/InfraMCP/atlassian-mcp-server/issues
Project-URL: Documentation, https://github.com/InfraMCP/atlassian-mcp-server#readme
Keywords: mcp,atlassian,jira,confluence,oauth,ai,assistant
Classifier: Development Status :: 4 - Beta
Classifier: Intended Audience :: Developers
Classifier: License :: OSI Approved :: MIT License
Classifier: Operating System :: OS Independent
Classifier: Programming Language :: Python :: 3
Classifier: Programming Language :: Python :: 3.10
Classifier: Programming Language :: Python :: 3.11
Classifier: Programming Language :: Python :: 3.12
Classifier: Topic :: Software Development :: Libraries :: Python Modules
Classifier: Topic :: Internet :: WWW/HTTP :: Dynamic Content
Classifier: Topic :: Office/Business
Requires-Python: >=3.10
License-File: LICENSE
Requires-Dist: mcp==1.24.0
Requires-Dist: httpx==0.28.1
Requires-Dist: pydantic==2.11.9
Requires-Dist: pydantic-settings==2.10.1
Provides-Extra: dev
Requires-Dist: pytest>=8.0.0; extra == "dev"
Requires-Dist: pytest-asyncio>=0.24.0; extra == "dev"
Requires-Dist: black>=24.0.0; extra == "dev"
Requires-Dist: isort>=5.13.0; extra == "dev"
Requires-Dist: mypy>=1.0.0; extra == "dev"
Requires-Dist: types-requests>=2.0.0; extra == "dev"
Requires-Dist: build>=0.10.0; extra == "dev"
Requires-Dist: twine>=4.0.0; extra == "dev"
Provides-Extra: security
Requires-Dist: safety>=3.0.0; extra == "security"
Requires-Dist: pip-audit>=2.6.0; extra == "security"
Dynamic: license-file
